simbricks/client/__init__.py
simbricks/client/auth.py
simbricks/client/client.py
simbricks/client/opus/base.py
simbricks/client/provider.py
simbricks/client/settings.py
simbricks_client-0.3.6.dist-info/METADATA
simbricks_client-0.3.6.dist-info/WHEEL
simbricks_client-0.3.6.dist-info/RECORD
